mathrtc/__init__.py
mathrtc/add_or_even.py
mathrtc/fib.py
mathrtc/main.py
mathrtc/palindrome.py
mathrtc-0.1.17.dist-info/licenses/LICENSE.txt
mathrtc-0.1.17.dist-info/WHEEL
mathrtc-0.1.17.dist-info/METADATA
mathrtc-0.1.17.dist-info/RECORD
