Metadata-Version: 2.4
Name: mathrtc
Version: 0.1.17
Summary: A sample package published using Flit
Author-email: Tamilvanan <tamil20122005@gmail.com>
Requires-Python: >=3.8
License-File: LICENSE.txt
